{"links":[{"source":0,"target":0,"value":1.0},{"source":0,"target":1,"value":0.872},{"source":0,"target":2,"value":0.926},{"source":0,"target":3,"value":0.942},{"source":0,"target":4,"value":0.895},{"source":0,"target":5,"value":0.4},{"source":1,"target":0,"value":0.872},{"source":1,"target":1,"value":0.939},{"source":1,"target":2,"value":0.885},{"source":1,"target":3,"value":0.92},{"source":1,"target":4,"value":0.897},{"source":1,"target":5,"value":0.375},{"source":2,"target":0,"value":0.926},{"source":2,"target":1,"value":0.865},{"source":2,"target":2,"value":1.0},{"source":2,"target":3,"value":0.958},{"source":2,"target":4,"value":0.984},{"source":2,"target":5,"value":0.364},{"source":3,"target":0,"value":0.942},{"source":3,"target":1,"value":0.9},{"source":3,"target":2,"value":0.972},{"source":3,"target":3,"value":0.976},{"source":3,"target":4,"value":0.947},{"source":3,"target":5,"value":0.409},{"source":4,"target":0,"value":0.895},{"source":4,"target":4,"value":0.986},{"source":4,"target":2,"value":0.984},{"source":4,"target":5,"value":0.457},{"source":4,"target":3,"value":0.93},{"source":4,"target":1,"value":0.872},{"source":5,"target":0,"value":0.4},{"source":5,"target":4,"value":0.457},{"source":5,"target":2,"value":0.364},{"source":5,"target":5,"value":1.0},{"source":5,"target":3,"value":0.409},{"source":5,"target":1,"value":0.344}],"nodes":[{"name":"Sarney Filho","uf":"MA"},{"name":"Leonardo Mattos","uf":"MG"},{"name":"Deley","uf":"RJ"},{"name":"Marcelo Ortiz","uf":"SP"},{"name":"Edson Duarte","uf":"BA"},{"name":"Jovino Cândido","uf":"SP"}],"stats":{"filtered_voting_sessions":109,"total_voting_sessions":125}}